dlchordx/__init__.py
dlchordx/chord.py
dlchordx/chord_prog.py
dlchordx/const.py
dlchordx/parser.py
test/__init__.py
test/test_chord.py
test/test_chord_parser.py
test/test_quality_parser.py
test/test_utils.py
dlchordx-1.0.5.dist-info/LICENSE
dlchordx-1.0.5.dist-info/METADATA
dlchordx-1.0.5.dist-info/WHEEL
dlchordx-1.0.5.dist-info/top_level.txt
dlchordx-1.0.5.dist-info/RECORD
